noble_tls/__init__.py
noble_tls/__version__.py
noble_tls/cookies.py
noble_tls/response.py
noble_tls/sessions.py
noble_tls/c/__init__.py
noble_tls/c/cffi.py
noble_tls/exceptions/__init__.py
noble_tls/exceptions/exceptions.py
noble_tls/tests/__init__.py
noble_tls/tests/test_asset.py
noble_tls/tests/test_cffi.py
noble_tls/tests/test_exceptions.py
noble_tls/tests/test_file_fetch.py
noble_tls/tests/test_response.py
noble_tls/tests/test_sessions.py
noble_tls/updater/__init__.py
noble_tls/updater/file_fetch.py
noble_tls/utils/__init__.py
noble_tls/utils/asset.py
noble_tls/utils/identifiers.py
noble_tls/utils/session_utils.py
noble_tls/utils/structures.py
noble_tls-0.1.5.dist-info/licenses/LICENSE
noble_tls-0.1.5.dist-info/METADATA
noble_tls-0.1.5.dist-info/WHEEL
noble_tls-0.1.5.dist-info/top_level.txt
noble_tls-0.1.5.dist-info/RECORD
